flyan/__init__.py
flyan/misc.py
flyan/ryanair.py
flyan-0.1.5.dist-info/METADATA
flyan-0.1.5.dist-info/WHEEL
flyan-0.1.5.dist-info/top_level.txt
flyan-0.1.5.dist-info/RECORD
