Metadata-Version: 2.4
Name: Flyan
Version: 0.1.5
Summary: Open source unofficial API wrappper to get flight data from RyanAir.
Requires-Python: >=3.8
Requires-Dist: fake-useragent>=1.5.1
Requires-Dist: httpx>=0.27.2
Requires-Dist: pydantic>=2.9.2
Requires-Dist: tenacity>=9.0.0
